patrowlhears4py/__init__.py
patrowlhears4py/api.py
patrowlhears4py/cli.py
patrowlhears4py/exceptions.py
patrowlhears4py/utils/__init__.py
patrowlhears4py/utils/pip.py
patrowlhears4py/utils/print.py
PatrowlHears4py-1.2.0.dist-info/LICENSE
PatrowlHears4py-1.2.0.dist-info/METADATA
PatrowlHears4py-1.2.0.dist-info/WHEEL
PatrowlHears4py-1.2.0.dist-info/dependency_links.txt
PatrowlHears4py-1.2.0.dist-info/entry_points.txt
PatrowlHears4py-1.2.0.dist-info/top_level.txt
PatrowlHears4py-1.2.0.dist-info/RECORD
