Metadata-Version: 2.1
Name: PatrowlHears4py
Version: 1.2.0
Summary: Python API client and CLI for PatrowlHears
Home-page: https://github.com/Patrowl/PatrowlHears4py
Author: Nicolas Mattiocco
Author-email: nicolas@patrowl.io
License: AGPLv3
Platform: UNKNOWN
Requires-Python: >=3.6
Requires-Dist: requests
Requires-Dist: click
Requires-Dist: pathlib
